ce_dates_parser/__init__.py
ce_dates_parser/dates_parser.py
ce_dates_parser/dates_regex.py
ce_dates_parser-0.0.7.dist-info/LICENSE
ce_dates_parser-0.0.7.dist-info/METADATA
ce_dates_parser-0.0.7.dist-info/WHEEL
ce_dates_parser-0.0.7.dist-info/top_level.txt
ce_dates_parser-0.0.7.dist-info/RECORD
