Metadata-Version: 2.1
Name: ce-dates-parser
Version: 0.0.7
Summary: Package with class to parse dates from text input
Author: Hello Astra
Author-email: dominik.stachura@onwelo.com
License: UNKNOWN
Platform: UNKNOWN
Classifier: Programming Language :: Python :: 3
Classifier: License :: OSI Approved :: MIT License
Classifier: Operating System :: OS Independent
Requires-Python: >=3.8
License-File: LICENSE
